gitdb/__init__.py
gitdb/base.py
gitdb/const.py
gitdb/exc.py
gitdb/fun.py
gitdb/pack.py
gitdb/stream.py
gitdb/typ.py
gitdb/util.py
gitdb/db/__init__.py
gitdb/db/base.py
gitdb/db/git.py
gitdb/db/loose.py
gitdb/db/mem.py
gitdb/db/pack.py
gitdb/db/ref.py
gitdb/test/__init__.py
gitdb/test/lib.py
gitdb/test/test_base.py
gitdb/test/test_example.py
gitdb/test/test_pack.py
gitdb/test/test_stream.py
gitdb/test/test_util.py
gitdb/utils/__init__.py
gitdb/utils/encoding.py
gitdb2-3.0.3.post1.dist-info/AUTHORS
gitdb2-3.0.3.post1.dist-info/LICENSE
gitdb2-3.0.3.post1.dist-info/METADATA
gitdb2-3.0.3.post1.dist-info/WHEEL
gitdb2-3.0.3.post1.dist-info/top_level.txt
gitdb2-3.0.3.post1.dist-info/RECORD
